<annotation>
	<folder>floorplan</folder>
	<filename>image-68701671-1.jpg</filename>
	<path>/Users/luluo/projects/floorplan/image-68701671-1.jpg</path>
	<source>
		<database>Unknown</database>
	</source>
	<size>
		<width>494</width>
		<height>600</height>
		<depth>3</depth>
	</size>
	<segmented>0</segmented>
	<object>
		<name>GrossArea</name>
		<pose>Unspecified</pose>
		<truncated>0</truncated>
		<difficult>0</difficult>
		<bndbox>
			<xmin>50</xmin>
			<ymin>44</ymin>
			<xmax>441</xmax>
			<ymax>67</ymax>
		</bndbox>
	</object>
</annotation>
